robo_chem_mcp/__init__.py
robo_chem_mcp/__main__.py
robo_chem_mcp/server.py
robo_chem_mcp-0.1.2.dist-info/METADATA
robo_chem_mcp-0.1.2.dist-info/WHEEL
robo_chem_mcp-0.1.2.dist-info/entry_points.txt
robo_chem_mcp-0.1.2.dist-info/top_level.txt
robo_chem_mcp-0.1.2.dist-info/RECORD
